main.py
weather_query_czy-0.1.0.dist-info/METADATA
weather_query_czy-0.1.0.dist-info/WHEEL
weather_query_czy-0.1.0.dist-info/entry_points.txt
weather_query_czy-0.1.0.dist-info/top_level.txt
weather_query_czy-0.1.0.dist-info/RECORD
