Metadata-Version: 2.4
Name: weather-query-czy
Version: 0.1.0
Summary: Add your description here
Requires-Python: >=3.12
Requires-Dist: build>=1.3.0
Requires-Dist: httpx>=0.28.1
Requires-Dist: mcp>=1.17.0
Requires-Dist: twine>=6.2.0
